pipzz/__init__.py
pipzz-0.1.dist-info/METADATA
pipzz-0.1.dist-info/WHEEL
pipzz-0.1.dist-info/top_level.txt
pipzz-0.1.dist-info/RECORD
