Metadata-Version: 2.1
Name: pipzz
Version: 0.1
Summary: pipzz: I sleep
Home-page: http://example.com
Author: Flying Circus
Author-email: flyingcircus@example.com
License: MIT
Platform: UNKNOWN
